setup.cfg
setup.py
pybble/__init__.py
pybble/setup.py
pybble.egg-info/PKG-INFO
pybble.egg-info/SOURCES.txt
pybble.egg-info/dependency_links.txt
pybble.egg-info/pbr.json
pybble.egg-info/requires.txt
pybble.egg-info/top_level.txt