Metadata-Version: 1.1
Name: pybble
Version: 0.1.2
Summary: A python API to the Rubble programming
Home-page: https: //github.com/viditeck/pybble
Author: Emlyn Clay
Author-email: emlyn@viditeck.com
License: MIT
Download-URL: https://github.com/viditeck/pybble/tarball/0.1.2
Keywords: rubble,logic language,api
Platform: UNKNOWN
